MANIFEST.in
README.md
license.txt
setup.cfg
setup.py
PyDatcom.egg-info/PKG-INFO
PyDatcom.egg-info/SOURCES.txt
PyDatcom.egg-info/dependency_links.txt
PyDatcom.egg-info/entry_points.txt
PyDatcom.egg-info/requires.txt
PyDatcom.egg-info/top_level.txt
pydatcom/__init__.py
pydatcom/exporter.py
pydatcom/parser.py
pydatcom/plotter.py
pydatcom/templates/modelica.mo
test/test.py
test/data/ASW-20.dcm
test/data/ASW-20.out
test/data/B-737.dcm
test/data/B-737.out
test/data/Citation.dcm
test/data/Citation.out
test/data/Citation_airfoil.dcm
test/data/Citation_simple.dcm
test/data/Citation_simple.out
test/data/Navion.dcm
test/data/Navion.out
test/data/SenecaII.dcm
test/data/SenecaII.out
test/data/canard.dcm
test/data/canard.out